Metadata-Version: 2.1
Name: surprisememore
Version: 0.1.0
Summary: SurpriseMeMore is a python module providing methods, based on the surprise framework, to detect mesoscale structures(e.g. communities, core-periphery, bow-tie) in graphs and multigraphs.
Home-page: https://github.com/EmilianoMarchese/SurpriseMeMore
Author: Emiliano Marchese
Author-email: emilianomarcheserc@gmail.com
License: MIT
Download-URL: https://github.com/EmilianoMarchese/SurpriseMeMore/archive/refs/tags/v0.1.0.zip
Keywords: community detection,core-periphery detection,graphs,multi-graphs,weighted graphs,surprise
Platform: UNKNOWN
Classifier: License :: OSI Approved :: MIT License
Classifier: Programming Language :: Python :: 3.6
Classifier: Programming Language :: Python :: 3.7
Classifier: Programming Language :: Python :: 3.8
Provides-Extra: dev
